amazon_textract_geofinder-0.0.8.data/scripts/amazon-textract-geofinder
textractgeofinder/__init__.py
textractgeofinder/_version.py
textractgeofinder/ocrdb.py
textractgeofinder/sample_patient_intake_form_parser.py
textractgeofinder/tgeofinder.py
textractgeofinder/tinterface.py
textractgeofinder/tword.py
amazon_textract_geofinder-0.0.8.dist-info/LICENSE
amazon_textract_geofinder-0.0.8.dist-info/METADATA
amazon_textract_geofinder-0.0.8.dist-info/WHEEL
amazon_textract_geofinder-0.0.8.dist-info/top_level.txt
amazon_textract_geofinder-0.0.8.dist-info/RECORD
