Metadata-Version: 2.1
Name: amazon-textract-geofinder
Version: 0.0.8
Summary: Amazon Textract package to easier access data through geometric information
Home-page: https://github.com/aws-samples/amazon-textract-textractor/tpipelinegeofinder
Author: Amazon Rekognition Textract Demoes
Author-email: rekognition-textract-demos@amazon.com
License: Apache License Version 2.0
Keywords: amazon-textract-textractor amazon textract finder geometry geo
Platform: UNKNOWN
Classifier: Development Status :: 4 - Beta
Classifier: Topic :: Utilities
Classifier: License :: OSI Approved :: Apache Software License
Classifier: Programming Language :: Python :: 3.6
Classifier: Programming Language :: Python :: 3.7
Classifier: Programming Language :: Python :: 3.8
Classifier: Programming Language :: Python :: 3.9
Requires-Python: >=3.6
Requires-Dist: amazon-textract-response-parser (>=0.1.17)
